[{"ID":2042,"CatID":1,"Exchange":"HOSE","IndustryName1":"Bán lẻ","IndustryName2":"Của hàng hàng hóa tổng hợp","IndustryName3":"Cửa hàng tổng hợp","Code":"BTT","Name":"CTCP Thương mại Dịch vụ Bến Thành","TotalShares":13500000,"URL":"https://finance.vietstock.vn/BTT-ctcp-thuong-mai-dich-vu-ben-thanh.htm","Row":151,"FirstTradeDate":"\/Date(1271178000000)\/","TotalRecord":1657},{"ID":3849,"CatID":5,"Exchange":"UPCoM","IndustryName1":"Dịch vụ hỗ trợ (hành chính, du lịch, an ninh, kiểm định…) và xử lý rác thải","IndustryName2":"Dịch vụ quản lý và tái chế chất thải","IndustryName3":"Thu gom chất thải","Code":"BTU","Name":"CTCP Công trình Đô thị Bến Tre","TotalShares":3600000,"URL":"https://finance.vietstock.vn/BTU-ctcp-cong-trinh-do-thi-ben-tre.htm","Row":152,"FirstTradeDate":"\/Date(1457629200000)\/","TotalRecord":1657},{"ID":3848,"CatID":5,"Exchange":"UPCoM","IndustryName1":"Dịch vụ lưu trú và ăn uống","IndustryName2":"Khách sạn và phòng ở","IndustryName3":"Chỗ ở cho khách du lịch","Code":"BTV","Name":"CTCP Dịch vụ Du lịch Bến Thành","TotalShares":25000000,"URL":"https://finance.vietstock.vn/BTV-ctcp-dich-vu-du-lich-ben-thanh.htm","Row":153,"FirstTradeDate":"\/Date(1488474000000)\/","TotalRecord":1657},{"ID":1307,"CatID":2,"Exchange":"HNX","IndustryName1":"Tiện ích","IndustryName2":"Nước, chất thải và các hệ thống khác","IndustryName3":"Hệ thống thủy lợi và cung cấp nước","Code":"BTW","Name":"CTCP Cấp nước Bến Thành","TotalShares":9360000,"URL":"https://finance.vietstock.vn/BTW-ctcp-cap-nuoc-ben-thanh.htm","Row":154,"FirstTradeDate":"\/Date(1510592400000)\/","TotalRecord":1657},{"ID":4623,"CatID":5,"Exchange":"UPCoM","IndustryName1":"Dịch vụ hỗ trợ (hành chính, du lịch, an ninh, kiểm định…) và xử lý rác thải","IndustryName2":"Dịch vụ quản lý và tái chế chất thải","IndustryName3":"Xử lý ô nhiễm và các dịch vụ quản lý chất thải khác","Code":"BUD","Name":"CTCP Khoa học Công nghệ Việt Nam","TotalShares":10000000,"URL":"https://finance.vietstock.vn/BUD-ctcp-khoa-hoc-cong-nghe-viet-nam.htm","Row":155,"FirstTradeDate":"\/Date(1522170000000)\/","TotalRecord":1657},{"ID":1197,"CatID":5,"Exchange":"UPCoM","IndustryName1":"Tài chính và bảo hiểm","IndustryName2":"Trung gian tín dụng và các hoạt động liên quan","IndustryName3":"Trung gian tín dụng có nhận tiền gửi","Code":"BVB","Name":"Ngân hàng TMCP Bản Việt","TotalShares":367090000,"URL":"https://finance.vietstock.vn/BVB-ngan-hang-tmcp-ban-viet.htm","Row":156,"FirstTradeDate":"\/Date(1594227600000)\/","TotalRecord":1657},{"ID":2626,"CatID":5,"Exchange":"UPCoM","IndustryName1":"Sản xuất","IndustryName2":"Sản xuất sản phẩm kim loại tổng hợp","IndustryName3":"Sản xuất kiến trúc và kết cấu kim loại","Code":"BVG","Name":"CTCP GROUP BẮC VIỆT","TotalShares":9750948,"URL":"https://finance.vietstock.vn/BVG-ctcp-group-bac-viet.htm","Row":157,"FirstTradeDate":"\/Date(1447952400000)\/","TotalRecord":1657},{"ID":1544,"CatID":1,"Exchange":"HOSE","IndustryName1":"Tài chính và bảo hiểm","IndustryName2":"Bảo hiểm và các hoạt động liên quan","IndustryName3":"Hãng bảo hiểm","Code":"BVH","Name":"Tập đoàn Bảo Việt","TotalShares":742322764,"URL":"https://finance.vietstock.vn/BVH-tap-doan-bao-viet.htm","Row":158,"FirstTradeDate":"\/Date(1245862800000)\/","TotalRecord":1657},{"ID":4867,"CatID":5,"Exchange":"UPCoM","IndustryName1":"Xây dựng và Bất động sản","IndustryName2":"Phát triển bất động sản","IndustryName3":"Phát triển bất động sản","Code":"BVL","Name":"CTCP BV Land","TotalShares":22000000,"URL":"https://finance.vietstock.vn/BVL-ctcp-bv-land.htm","Row":159,"FirstTradeDate":"\/Date(1623344400000)\/","TotalRecord":1657},{"ID":2340,"CatID":5,"Exchange":"UPCoM","IndustryName1":"Sản xuất","IndustryName2":"Sản xuất sợi, vải","IndustryName3":"Sản xuất sợi, vải thành phẩm","Code":"BVN","Name":"CTCP Bông Việt Nam","TotalShares":5000000,"URL":"https://finance.vietstock.vn/BVN-ctcp-bong-viet-nam.htm","Row":160,"FirstTradeDate":"\/Date(1318266000000)\/","TotalRecord":1657},{"ID":897,"CatID":2,"Exchange":"HNX","IndustryName1":"Tài chính và bảo hiểm","IndustryName2":"Môi giới chứng khoán, hàng hóa, đầu tư tài chính khác và các hoạt động liên quan","IndustryName3":"Môi giới chứng khoán và hàng hóa","Code":"BVS","Name":"CTCP Chứng khoán Bảo Việt","TotalShares":72233937,"URL":"https://finance.vietstock.vn/BVS-ctcp-chung-khoan-bao-viet.htm","Row":161,"FirstTradeDate":"\/Date(1166374800000)\/","TotalRecord":1657},{"ID":2547,"CatID":5,"Exchange":"UPCoM","IndustryName1":"Tiện ích","IndustryName2":"Nước, chất thải và các hệ thống khác","IndustryName3":"Hệ thống thủy lợi và cung cấp nước","Code":"BWA","Name":"CTCP Cấp thoát nước và Xây dựng Bảo Lộc","TotalShares":2700000,"URL":"https://finance.vietstock.vn/BWA-ctcp-cap-thoat-nuoc-va-xay-dung-bao-loc.htm","Row":162,"FirstTradeDate":"\/Date(1276448400000)\/","TotalRecord":1657},{"ID":4355,"CatID":1,"Exchange":"HOSE","IndustryName1":"Tiện ích","IndustryName2":"Nước, chất thải và các hệ thống khác","IndustryName3":"Hệ thống thủy lợi và cung cấp nước","Code":"BWE","Name":"CTCP Nước - Môi trường Bình Dương","TotalShares":192920000,"URL":"https://finance.vietstock.vn/BWE-ctcp-nuoc-moi-truong-binh-duong.htm","Row":163,"FirstTradeDate":"\/Date(1500483600000)\/","TotalRecord":1657},{"ID":2440,"CatID":5,"Exchange":"UPCoM","IndustryName1":"Tiện ích","IndustryName2":"Nước, chất thải và các hệ thống khác","IndustryName3":"Hệ thống thủy lợi và cung cấp nước","Code":"BWS","Name":"CTCP Cấp nước Bà Rịa - Vũng Tàu","TotalShares":90000000,"URL":"https://finance.vietstock.vn/BWS-ctcp-cap-nuoc-ba-ria-vung-tau.htm","Row":164,"FirstTradeDate":"\/Date(1511802000000)\/","TotalRecord":1657},{"ID":1563,"CatID":2,"Exchange":"HNX","IndustryName1":"Sản xuất","IndustryName2":"Sản xuất giấy","IndustryName3":"Sản xuất các sản phẩm từ giấy","Code":"BXH","Name":"CTCP VICEM Bao bì Hải Phòng","TotalShares":3012040,"URL":"https://finance.vietstock.vn/BXH-ctcp-vicem-bao-bi-hai-phong.htm","Row":165,"FirstTradeDate":"\/Date(1259082000000)\/","TotalRecord":1657},{"ID":4739,"CatID":5,"Exchange":"UPCoM","IndustryName1":"Vận tải và kho bãi","IndustryName2":"Hỗ trợ vận tải","IndustryName3":"Hoạt động hỗ trợ vận tải đường bộ","Code":"BXT","Name":"CTCP Bến xe Tàu Hậu Giang","TotalShares":63400,"URL":"https://finance.vietstock.vn/BXT-ctcp-ben-xe-tau-hau-giang.htm","Row":166,"FirstTradeDate":"\/Date(1560099600000)\/","TotalRecord":1657},{"ID":2928,"CatID":5,"Exchange":"UPCoM","IndustryName1":"Xây dựng và Bất động sản","IndustryName2":"Xây dựng công nghiệp nặng và dân dụng","IndustryName3":"Xây dựng cầu đường, đường cao tốc","Code":"C12","Name":"CTCP Cầu 12","TotalShares":4850000,"URL":"https://finance.vietstock.vn/C12-ctcp-cau-12.htm","Row":167,"FirstTradeDate":"\/Date(1482685200000)\/","TotalRecord":1657},{"ID":2003,"CatID":5,"Exchange":"UPCoM","IndustryName1":"Xây dựng và Bất động sản","IndustryName2":"Phát triển bất động sản","IndustryName3":"Phát triển bất động sản","Code":"C21","Name":"CTCP Thế Kỷ 21 ","TotalShares":19336371,"URL":"https://finance.vietstock.vn/C21-ctcp-the-ky-21.htm","Row":168,"FirstTradeDate":"\/Date(1477933200000)\/","TotalRecord":1657},{"ID":4679,"CatID":5,"Exchange":"UPCoM","IndustryName1":"Sản xuất","IndustryName2":"Sản xuất thực phẩm","IndustryName3":"Sản xuất đường và bánh kẹo","Code":"C22","Name":"CTCP 22","TotalShares":3550000,"URL":"https://finance.vietstock.vn/C22-ctcp-22.htm","Row":169,"FirstTradeDate":"\/Date(1527094800000)\/","TotalRecord":1657},{"ID":2055,"CatID":1,"Exchange":"HOSE","IndustryName1":"Khai khoáng","IndustryName2":"Khai khoáng (ngoại trừ dầu mỏ và khí đốt)","IndustryName3":"Khai thác đá và khoáng sản phi kim","Code":"C32","Name":"CTCP CIC39","TotalShares":15030145,"URL":"https://finance.vietstock.vn/C32-ctcp-cic39.htm","Row":170,"FirstTradeDate":"\/Date(1354208400000)\/","TotalRecord":1657},{"ID":2848,"CatID":5,"Exchange":"UPCoM","IndustryName1":"Xây dựng và Bất động sản","IndustryName2":"Xây dựng công nghiệp nặng và dân dụng","IndustryName3":"Xây dựng cầu đường, đường cao tốc","Code":"C36","Name":"CTCP Quản lý và Xây dựng Công trình Giao thông 236","TotalShares":1123500,"URL":"https://finance.vietstock.vn/C36-ctcp-quan-ly-va-xay-dung-cong-trinh-giao-thong-236.htm","Row":171,"FirstTradeDate":"\/Date(1496163600000)\/","TotalRecord":1657},{"ID":2120,"CatID":1,"Exchange":"HOSE","IndustryName1":"Xây dựng và Bất động sản","IndustryName2":"Xây dựng công nghiệp nặng và dân dụng","IndustryName3":"Xây dựng công nghiệp nặng và dân dụng khác","Code":"C47","Name":"CTCP Xây dựng 47","TotalShares":18722143,"URL":"https://finance.vietstock.vn/C47-ctcp-xay-dung-47.htm","Row":172,"FirstTradeDate":"\/Date(1301418000000)\/","TotalRecord":1657},{"ID":3803,"CatID":5,"Exchange":"UPCoM","IndustryName1":"Xây dựng và Bất động sản","IndustryName2":"Xây dựng công nghiệp nặng và dân dụng","IndustryName3":"Xây dựng cầu đường, đường cao tốc","Code":"C4G","Name":"CTCP Tập đoàn CIENCO4","TotalShares":105999914,"URL":"https://finance.vietstock.vn/C4G-ctcp-tap-doan-cienco4.htm","Row":173,"FirstTradeDate":"\/Date(1544374800000)\/","TotalRecord":1657},{"ID":4397,"CatID":2,"Exchange":"HNX","IndustryName1":"Xây dựng và Bất động sản","IndustryName2":"Xây dựng nhà cửa, cao ốc","IndustryName3":"Xây dựng công trình khác","Code":"C69","Name":"CTCP Xây dựng 1369","TotalShares":30000000,"URL":"https://finance.vietstock.vn/C69-ctcp-xay-dung-1369.htm","Row":174,"FirstTradeDate":"\/Date(1492707600000)\/","TotalRecord":1657},{"ID":3000,"CatID":5,"Exchange":"UPCoM","IndustryName1":"Xây dựng và Bất động sản","IndustryName2":"Xây dựng công nghiệp nặng và dân dụng","IndustryName3":"Xây dựng cầu đường, đường cao tốc","Code":"C71","Name":"CTCP 471","TotalShares":5000000,"URL":"https://finance.vietstock.vn/C71-ctcp-471.htm","Row":175,"FirstTradeDate":"\/Date(1438534800000)\/","TotalRecord":1657},{"ID":1028,"CatID":2,"Exchange":"HNX","IndustryName1":"Xây dựng và Bất động sản","IndustryName2":"Xây dựng công nghiệp nặng và dân dụng","IndustryName3":"Xây dựng cầu đường, đường cao tốc","Code":"C92","Name":"CTCP Xây dựng và Đầu tư 492","TotalShares":5312920,"URL":"https://finance.vietstock.vn/C92-ctcp-xay-dung-va-dau-tu-492.htm","Row":176,"FirstTradeDate":"\/Date(1195405200000)\/","TotalRecord":1657},{"ID":4665,"CatID":5,"Exchange":"UPCoM","IndustryName1":"Công nghệ và thông tin","IndustryName2":"Phát sóng - Ngoại trừ internet","IndustryName3":"Truyền hình cáp và các chương trình thuê bao khác","Code":"CAB","Name":"CTCP Tổng Công ty Truyền hình Cáp Việt Nam","TotalShares":45745876,"URL":"https://finance.vietstock.vn/CAB-ctcp-tong-cong-ty-truyen-hinh-cap-viet-nam.htm","Row":177,"FirstTradeDate":"\/Date(1567702800000)\/","TotalRecord":1657},{"ID":1454,"CatID":5,"Exchange":"UPCoM","IndustryName1":"Sản xuất","IndustryName2":"Sản xuất thực phẩm","IndustryName3":"Sơ chế và đóng gói thủy sản","Code":"CAD","Name":"CTCP Chế biến và Xuất nhập khẩu Thủy sản Cadovimex","TotalShares":8799927,"URL":"https://finance.vietstock.vn/CAD-ctcp-che-bien-va-xuat-nhap-khau-thuy-san-cadovimex.htm","Row":178,"FirstTradeDate":"\/Date(1351702800000)\/","TotalRecord":1657},{"ID":4504,"CatID":2,"Exchange":"HNX","IndustryName1":"Vận tải và kho bãi","IndustryName2":"Hỗ trợ vận tải","IndustryName3":"Sắp xếp vận tải hàng hóa","Code":"CAG","Name":"CTCP Cảng An Giang","TotalShares":13800000,"URL":"https://finance.vietstock.vn/CAG-ctcp-cang-an-giang.htm","Row":179,"FirstTradeDate":"\/Date(1512320400000)\/","TotalRecord":1657},{"ID":4178,"CatID":5,"Exchange":"UPCoM","IndustryName1":"Tiện ích","IndustryName2":"Nước, chất thải và các hệ thống khác","IndustryName3":"Hệ thống thủy lợi và cung cấp nước","Code":"CAM","Name":"CTCP Môi trường đô thị Cà Mau","TotalShares":14400,"URL":"https://finance.vietstock.vn/CAM-ctcp-moi-truong-do-thi-ca-mau.htm","Row":180,"FirstTradeDate":"\/Date(1565110800000)\/","TotalRecord":1657},{"ID":48,"CatID":2,"Exchange":"HNX","IndustryName1":"Sản xuất","IndustryName2":"Sản xuất thực phẩm","IndustryName3":"Bảo quản rau quả và sản xuất thực phẩm chuyên biệt","Code":"CAN","Name":"CTCP Đồ hộp Hạ Long","TotalShares":5000000,"URL":"https://finance.vietstock.vn/CAN-ctcp-do-hop-ha-long.htm","Row":181,"FirstTradeDate":"\/Date(1244739600000)\/","TotalRecord":1657},{"ID":1029,"CatID":2,"Exchange":"HNX","IndustryName1":"Sản xuất","IndustryName2":"Sản xuất giấy","IndustryName3":"Nhà máy sản xuất bột giấy, giấy và giấy bìa","Code":"CAP","Name":"CTCP Lâm Nông sản Thực phẩm Yên Bái","TotalShares":5236023,"URL":"https://finance.vietstock.vn/CAP-ctcp-lam-nong-san-thuc-pham-yen-bai.htm","Row":182,"FirstTradeDate":"\/Date(1199811600000)\/","TotalRecord":1657},{"ID":1259,"CatID":5,"Exchange":"UPCoM","IndustryName1":"Sản xuất","IndustryName2":"Sản xuất thực phẩm","IndustryName3":"Sơ chế và đóng gói thủy sản","Code":"CAT","Name":"CTCP Thủy sản Cà Mau","TotalShares":9748579,"URL":"https://finance.vietstock.vn/CAT-ctcp-thuy-san-ca-mau.htm","Row":183,"FirstTradeDate":"\/Date(1521738000000)\/","TotalRecord":1657},{"ID":1283,"CatID":2,"Exchange":"HNX","IndustryName1":"Sản xuất","IndustryName2":"Sản xuất trang thiết bị, dụng cụ điện","IndustryName3":"Sản xuất các thiết bị điện và dụng cụ khác","Code":"CAV","Name":"CTCP Dây Cáp điện Việt Nam","TotalShares":57600000,"URL":"https://finance.vietstock.vn/CAV-ctcp-day-cap-dien-viet-nam.htm","Row":184,"FirstTradeDate":"\/Date(1417971600000)\/","TotalRecord":1657},{"ID":4562,"CatID":5,"Exchange":"UPCoM","IndustryName1":"Sản xuất","IndustryName2":"Sản xuất các sản phẩm kim loại cơ bản","IndustryName3":"Sản xuất sắt, thép và hợp kim fero","Code":"CBI","Name":"CTCP Gang thép Cao Bằng","TotalShares":43006366,"URL":"https://finance.vietstock.vn/CBI-ctcp-gang-thep-cao-bang.htm","Row":185,"FirstTradeDate":"\/Date(1506531600000)\/","TotalRecord":1657},{"ID":3337,"CatID":5,"Exchange":"UPCoM","IndustryName1":"Sản xuất","IndustryName2":"Sản xuất thực phẩm","IndustryName3":"Sản xuất đường và bánh kẹo","Code":"CBS","Name":"CTCP Mía Đường Cao Bằng","TotalShares":3527925,"URL":"https://finance.vietstock.vn/CBS-ctcp-mia-duong-cao-bang.htm","Row":186,"FirstTradeDate":"\/Date(1497891600000)\/","TotalRecord":1657},{"ID":4343,"CatID":5,"Exchange":"UPCoM","IndustryName1":"Xây dựng và Bất động sản","IndustryName2":"Xây dựng công nghiệp nặng và dân dụng","IndustryName3":"Xây dựng công nghiệp nặng và dân dụng khác","Code":"CC1","Name":"Tổng Công ty Xây dựng Số 1 - CTCP","TotalShares":110000000,"URL":"https://finance.vietstock.vn/CC1-tong-cong-ty-xay-dung-so-1-ctcp.htm","Row":187,"FirstTradeDate":"\/Date(1500483600000)\/","TotalRecord":1657},{"ID":2253,"CatID":5,"Exchange":"UPCoM","IndustryName1":"Xây dựng và Bất động sản","IndustryName2":"Xây dựng nhà cửa, cao ốc","IndustryName3":"Xây dựng nhà ở, khu dân cư, cao ốc","Code":"CC4","Name":"CTCP Đầu tư và Xây dựng Số 4","TotalShares":32000000,"URL":"https://finance.vietstock.vn/CC4-ctcp-dau-tu-va-xay-dung-so-4.htm","Row":188,"FirstTradeDate":"\/Date(1501174800000)\/","TotalRecord":1657},{"ID":3004,"CatID":5,"Exchange":"UPCoM","IndustryName1":"Sản xuất","IndustryName2":"Sản xuất thực phẩm","IndustryName3":"Sơ chế và đóng gói thủy sản","Code":"CCA","Name":"CTCP Xuất nhập khẩu Thuỷ sản Cần Thơ","TotalShares":15092326,"URL":"https://finance.vietstock.vn/CCA-ctcp-xuat-nhap-khau-thuy-san-can-tho.htm","Row":189,"FirstTradeDate":"\/Date(1577293200000)\/","TotalRecord":1657},{"ID":1277,"CatID":1,"Exchange":"HOSE","IndustryName1":"Bán lẻ","IndustryName2":"Trạm xăng","IndustryName3":"Trạm xăng có cửa hàng tiện lợi","Code":"CCI","Name":"CTCP Đầu tư Phát triển Công nghiệp Thương mại Củ Chi","TotalShares":17743865,"URL":"https://finance.vietstock.vn/CCI-ctcp-dau-tu-phat-trien-cong-nghiep-thuong-mai-cu-chi.htm","Row":190,"FirstTradeDate":"\/Date(1271264400000)\/","TotalRecord":1657},{"ID":2710,"CatID":1,"Exchange":"HOSE","IndustryName1":"Xây dựng và Bất động sản","IndustryName2":"Bất động sản ","IndustryName3":"Các hoạt động liên quan đến bất động sản","Code":"CCL","Name":"CTCP Đầu Tư và Phát triển Đô Thị Dầu khí Cửu Long","TotalShares":47499885,"URL":"https://finance.vietstock.vn/CCL-ctcp-dau-tu-va-phat-trien-do-thi-dau-khi-cuu-long.htm","Row":191,"FirstTradeDate":"\/Date(1299085200000)\/","TotalRecord":1657},{"ID":1312,"CatID":5,"Exchange":"UPCoM","IndustryName1":"Sản xuất","IndustryName2":"Sản xuất sản phẩm khoáng chất phi kim","IndustryName3":"Sản xuất xi măng và các sản phẩm bê tông","Code":"CCM","Name":"CTCP khoáng sản và Xi măng Cần Thơ","TotalShares":6199900,"URL":"https://finance.vietstock.vn/CCM-ctcp-khoang-san-va-xi-mang-can-tho.htm","Row":192,"FirstTradeDate":"\/Date(1530810000000)\/","TotalRecord":1657},{"ID":1638,"CatID":5,"Exchange":"UPCoM","IndustryName1":"Vận tải và kho bãi","IndustryName2":"Hỗ trợ vận tải","IndustryName3":"Các hoạt động hỗ trợ vận tải khác","Code":"CCP","Name":"CTCP Cảng Cửa Cấm Hải Phòng","TotalShares":2400000,"URL":"https://finance.vietstock.vn/CCP-ctcp-cang-cua-cam-hai-phong.htm","Row":193,"FirstTradeDate":"\/Date(1489597200000)\/","TotalRecord":1657},{"ID":3999,"CatID":5,"Exchange":"UPCoM","IndustryName1":"Vận tải và kho bãi","IndustryName2":"Hỗ trợ vận tải","IndustryName3":"Hoạt động hỗ trợ vận tải đường thủy","Code":"CCR","Name":"CTCP Cảng Cam Ranh","TotalShares":24501817,"URL":"https://finance.vietstock.vn/CCR-ctcp-cang-cam-ranh.htm","Row":194,"FirstTradeDate":"\/Date(1443027600000)\/","TotalRecord":1657},{"ID":3878,"CatID":5,"Exchange":"UPCoM","IndustryName1":"Vận tải và kho bãi","IndustryName2":"Hỗ trợ vận tải","IndustryName3":"Sắp xếp vận tải hàng hóa","Code":"CCT","Name":"CTCP Cảng Cần Thơ","TotalShares":28480000,"URL":"https://finance.vietstock.vn/CCT-ctcp-cang-can-tho.htm","Row":195,"FirstTradeDate":"\/Date(1498755600000)\/","TotalRecord":1657},{"ID":3835,"CatID":5,"Exchange":"UPCoM","IndustryName1":"Dịch vụ chuyên môn, khoa học và công nghệ","IndustryName2":"Kiến trúc, tư vấn xây dựng và dịch vụ liên quan","IndustryName3":"Dịch vụ tư vấn xây dựng","Code":"CCV","Name":"CTCP Tư vấn Xây dựng Công nghiệp và Đô thị Việt Nam","TotalShares":1800000,"URL":"https://finance.vietstock.vn/CCV-ctcp-tu-van-xay-dung-cong-nghiep-va-do-thi-viet-nam.htm","Row":196,"FirstTradeDate":"\/Date(1483894800000)\/","TotalRecord":1657},{"ID":1031,"CatID":1,"Exchange":"HOSE","IndustryName1":"Xây dựng và Bất động sản","IndustryName2":"Phát triển bất động sản","IndustryName3":"Phát triển bất động sản","Code":"CDC","Name":"CTCP Chương Dương","TotalShares":21988716,"URL":"https://finance.vietstock.vn/CDC-ctcp-chuong-duong.htm","Row":197,"FirstTradeDate":"\/Date(1284310800000)\/","TotalRecord":1657},{"ID":2284,"CatID":5,"Exchange":"UPCoM","IndustryName1":"Sản xuất","IndustryName2":"Sản xuất sản phẩm khoáng chất phi kim","IndustryName3":"Sản xuất các sản phẩm từ đất sét và vật liệu chịu nhiệt","Code":"CDG","Name":"CTCP Cầu Đuống","TotalShares":3464995,"URL":"https://finance.vietstock.vn/CDG-ctcp-cau-duong.htm","Row":198,"FirstTradeDate":"\/Date(1488128400000)\/","TotalRecord":1657},{"ID":4324,"CatID":5,"Exchange":"UPCoM","IndustryName1":"Dịch vụ hỗ trợ (hành chính, du lịch, an ninh, kiểm định…) và xử lý rác thải","IndustryName2":"Dịch vụ quản lý và tái chế chất thải","IndustryName3":"Thu gom chất thải","Code":"CDH","Name":"CTCP Công trình Công cộng và Dịch vụ Du lịch Hải Phòng","TotalShares":2000000,"URL":"https://finance.vietstock.vn/CDH-ctcp-cong-trinh-cong-cong-va-dich-vu-du-lich-hai-phong.htm","Row":199,"FirstTradeDate":"\/Date(1466614800000)\/","TotalRecord":1657},{"ID":3777,"CatID":2,"Exchange":"HNX","IndustryName1":"Vận tải và kho bãi","IndustryName2":"Hỗ trợ vận tải","IndustryName3":"Sắp xếp vận tải hàng hóa","Code":"CDN","Name":"CTCP Cảng Đà Nẵng","TotalShares":99000000,"URL":"https://finance.vietstock.vn/CDN-ctcp-cang-da-nang.htm","Row":200,"FirstTradeDate":"\/Date(1480438800000)\/","TotalRecord":1657}]