[{"ID":3982,"CatID":5,"Exchange":"UPCoM","IndustryName1":"Bán buôn","IndustryName2":"Bán buôn hàng lâu bền","IndustryName3":"Bán buôn gỗ xẻ và vật liệu xây dựng khác","Code":"CDO","Name":"CTCP Tư vấn Thiết kế và Phát triển Đô thị","TotalShares":31504975,"URL":"https://finance.vietstock.vn/CDO-ctcp-tu-van-thiet-ke-va-phat-trien-do-thi.htm","Row":201,"FirstTradeDate":"\/Date(1538672400000)\/","TotalRecord":1657},{"ID":2524,"CatID":5,"Exchange":"UPCoM","IndustryName1":"Bán buôn","IndustryName2":"Bán buôn hàng tiêu dùng","IndustryName3":"Bán buôn dược phẩm và tạp hóa dược","Code":"CDP","Name":"CTCP Dược phẩm Trung ương Codupha","TotalShares":18270000,"URL":"https://finance.vietstock.vn/CDP-ctcp-duoc-pham-trung-uong-codupha.htm","Row":202,"FirstTradeDate":"\/Date(1531414800000)\/","TotalRecord":1657},{"ID":3228,"CatID":5,"Exchange":"UPCoM","IndustryName1":"Xây dựng và Bất động sản","IndustryName2":"Xây dựng công nghiệp nặng và dân dụng","IndustryName3":"Xây dựng công nghiệp nặng và dân dụng khác","Code":"CDR","Name":"CTCP Xây dựng Cao su Đồng Nai","TotalShares":1600000,"URL":"https://finance.vietstock.vn/CDR-ctcp-xay-dung-cao-su-dong-nai.htm","Row":203,"FirstTradeDate":"\/Date(1498410000000)\/","TotalRecord":1657},{"ID":3010,"CatID":5,"Exchange":"UPCoM","IndustryName1":"Sản xuất","IndustryName2":"Sản xuất thiết bị, máy móc","IndustryName3":"Sản xuất thiết bị, máy móc công nghiệp","Code":"CE1","Name":"CTCP Xây dựng và Thiết bị Công nghiệp CIE1","TotalShares":6000000,"URL":"https://finance.vietstock.vn/CE1-ctcp-xay-dung-va-thiet-bi-cong-nghiep-cie1.htm","Row":204,"FirstTradeDate":"\/Date(1491757200000)\/","TotalRecord":1657},{"ID":4468,"CatID":1,"Exchange":"HOSE","IndustryName1":"Xây dựng và Bất động sản","IndustryName2":"Xây dựng công nghiệp nặng và dân dụng","IndustryName3":"Xây dựng cầu đường, đường cao tốc","Code":"CEE","Name":"CTCP Xây dựng Hạ tầng CII","TotalShares":41500000,"URL":"https://finance.vietstock.vn/CEE-ctcp-xay-dung-ha-tang-cii.htm","Row":205,"FirstTradeDate":"\/Date(1494781200000)\/","TotalRecord":1657},{"ID":2005,"CatID":5,"Exchange":"UPCoM","IndustryName1":"Sản xuất","IndustryName2":"Sản xuất thiết bị, máy móc","IndustryName3":"Sản xuất thiết bị, máy móc công nghiệp","Code":"CEG","Name":"CTCP Tập đoàn Xây dựng và Thiết bị Công nghiệp","TotalShares":3800000,"URL":"https://finance.vietstock.vn/CEG-ctcp-tap-doan-xay-dung-va-thiet-bi-cong-nghiep.htm","Row":206,"FirstTradeDate":"\/Date(1494954000000)\/","TotalRecord":1657},{"ID":4685,"CatID":5,"Exchange":"UPCoM","IndustryName1":"Bán buôn","IndustryName2":"Bán buôn hàng tiêu dùng","IndustryName3":"Bán buôn thực phẩm, tạp hóa và các sản phẩm có liên quan","Code":"CEN","Name":"CTCP CENCON Việt Nam","TotalShares":3809200,"URL":"https://finance.vietstock.vn/CEN-ctcp-cencon-viet-nam.htm","Row":207,"FirstTradeDate":"\/Date(1528995600000)\/","TotalRecord":1657},{"ID":3345,"CatID":2,"Exchange":"HNX","IndustryName1":"Xây dựng và Bất động sản","IndustryName2":"Phát triển bất động sản","IndustryName3":"Phát triển bất động sản","Code":"CEO","Name":"CTCP Tập đoàn C.E.O","TotalShares":257339985,"URL":"https://finance.vietstock.vn/CEO-ctcp-tap-doan-c-e-o.htm","Row":208,"FirstTradeDate":"\/Date(1411923600000)\/","TotalRecord":1657},{"ID":4380,"CatID":2,"Exchange":"HNX","IndustryName1":"Sản xuất","IndustryName2":"Sản xuất khác","IndustryName3":"Sản xuất khác","Code":"CET","Name":"CTCP HTC Holding","TotalShares":6050000,"URL":"https://finance.vietstock.vn/CET-ctcp-htc-holding.htm","Row":209,"FirstTradeDate":"\/Date(1501174800000)\/","TotalRecord":1657},{"ID":1779,"CatID":5,"Exchange":"UPCoM","IndustryName1":"Sản xuất","IndustryName2":"Sản xuất thực phẩm","IndustryName3":"Sơ chế và đóng gói thủy sản","Code":"CFC","Name":"CTCP Cafico Việt Nam","TotalShares":2443680,"URL":"https://finance.vietstock.vn/CFC-ctcp-cafico-viet-nam.htm","Row":210,"FirstTradeDate":"\/Date(1245776400000)\/","TotalRecord":1657},{"ID":4853,"CatID":5,"Exchange":"UPCoM","IndustryName1":"Dịch vụ giáo dục","IndustryName2":"Dịch vụ giáo dục","IndustryName3":"Các trường và cơ sở giáo dục khác","Code":"CFM","Name":"CTCP Đầu tư CFM","TotalShares":2000000,"URL":"https://finance.vietstock.vn/CFM-ctcp-dau-tu-cfm.htm","Row":211,"FirstTradeDate":"\/Date(1611507600000)\/","TotalRecord":1657},{"ID":4735,"CatID":5,"Exchange":"UPCoM","IndustryName1":"Sản xuất","IndustryName2":"Sản xuất thực phẩm","IndustryName3":"Sản xuất các loại thực phẩm khác","Code":"CFV","Name":"CTCP Cà phê Thắng Lợi","TotalShares":6256100,"URL":"https://finance.vietstock.vn/CFV-ctcp-ca-phe-thang-loi.htm","Row":212,"FirstTradeDate":"\/Date(1559494800000)\/","TotalRecord":1657},{"ID":1731,"CatID":5,"Exchange":"UPCoM","IndustryName1":"Bán buôn","IndustryName2":"Bán buôn hàng lâu bền","IndustryName3":"Bán buôn máy móc, thiết bị và vật tư","Code":"CGL","Name":"CTCP Thương mại Gia Lai","TotalShares":1880000,"URL":"https://finance.vietstock.vn/CGL-ctcp-thuong-mai-gia-lai.htm","Row":213,"FirstTradeDate":"\/Date(1606928400000)\/","TotalRecord":1657},{"ID":2141,"CatID":5,"Exchange":"UPCoM","IndustryName1":"Sản xuất","IndustryName2":"Sản xuất sản phẩm khoáng chất phi kim","IndustryName3":"Sản xuất các sản phẩm từ đất sét và vật liệu chịu nhiệt","Code":"CGV","Name":"CTCP Sành sứ Thủy tinh Việt Nam","TotalShares":9499956,"URL":"https://finance.vietstock.vn/CGV-ctcp-sanh-su-thuy-tinh-viet-nam.htm","Row":214,"FirstTradeDate":"\/Date(1497978000000)\/","TotalRecord":1657},{"ID":2793,"CatID":5,"Exchange":"UPCoM","IndustryName1":"Xây dựng và Bất động sản","IndustryName2":"Xây dựng nhà cửa, cao ốc","IndustryName3":"Xây dựng công trình khác","Code":"CH5","Name":"CTCP Xây dựng Số 5 Hà Nội","TotalShares":3732450,"URL":"https://finance.vietstock.vn/CH5-ctcp-xay-dung-so-5-ha-noi.htm","Row":215,"FirstTradeDate":"\/Date(1497373200000)\/","TotalRecord":1657},{"ID":2936,"CatID":5,"Exchange":"UPCoM","IndustryName1":"Sản xuất","IndustryName2":"Sản xuất các sản phẩm gỗ","IndustryName3":"Sản xuất các sản phẩm gỗ khác","Code":"CHC","Name":"CTCP Cẩm Hà","TotalShares":2720000,"URL":"https://finance.vietstock.vn/CHC-ctcp-cam-ha.htm","Row":216,"FirstTradeDate":"\/Date(1487178000000)\/","TotalRecord":1657},{"ID":2123,"CatID":1,"Exchange":"HOSE","IndustryName1":"Tiện ích","IndustryName2":"Phát, truyền tải và phân phối điện năng","IndustryName3":"Truyền tải, kiểm soát và phân phối điện ","Code":"CHP","Name":"CTCP Thủy điện Miền Trung","TotalShares":146912668,"URL":"https://finance.vietstock.vn/CHP-ctcp-thuy-dien-mien-trung.htm","Row":217,"FirstTradeDate":"\/Date(1475082000000)\/","TotalRecord":1657},{"ID":4242,"CatID":5,"Exchange":"UPCoM","IndustryName1":"Xây dựng và Bất động sản","IndustryName2":"Xây dựng nhà cửa, cao ốc","IndustryName3":"Xây dựng công trình khác","Code":"CHS","Name":"CTCP Chiếu sáng Công cộng Thành phố Hồ Chí Minh","TotalShares":28400000,"URL":"https://finance.vietstock.vn/CHS-ctcp-chieu-sang-cong-cong-thanh-pho-ho-chi-minh.htm","Row":218,"FirstTradeDate":"\/Date(1484154000000)\/","TotalRecord":1657},{"ID":2827,"CatID":5,"Exchange":"UPCoM","IndustryName1":"Xây dựng và Bất động sản","IndustryName2":"Xây dựng công nghiệp nặng và dân dụng","IndustryName3":"Xây dựng công nghiệp nặng và dân dụng khác","Code":"CI5","Name":"CTCP Đầu Tư Xây dựng Số 5","TotalShares":2700000,"URL":"https://finance.vietstock.vn/CI5-ctcp-dau-tu-xay-dung-so-5.htm","Row":219,"FirstTradeDate":"\/Date(1309453200000)\/","TotalRecord":1657},{"ID":4510,"CatID":2,"Exchange":"HNX","IndustryName1":"Bán lẻ","IndustryName2":"Của hàng hàng hóa tổng hợp","IndustryName3":"Các cửa hàng hàng hóa khác","Code":"CIA","Name":"CTCP Dịch vụ Sân bay Quốc tế Cam Ranh","TotalShares":19709904,"URL":"https://finance.vietstock.vn/CIA-ctcp-dich-vu-san-bay-quoc-te-cam-ranh.htm","Row":220,"FirstTradeDate":"\/Date(1511888400000)\/","TotalRecord":1657},{"ID":899,"CatID":5,"Exchange":"UPCoM","IndustryName1":"Xây dựng và Bất động sản","IndustryName2":"Bất động sản ","IndustryName3":"Cho thuê bất động sản","Code":"CID","Name":"CTCP Xây dựng và Phát triển Cơ sở Hạ tầng","TotalShares":1082000,"URL":"https://finance.vietstock.vn/CID-ctcp-xay-dung-va-phat-trien-co-so-ha-tang.htm","Row":221,"FirstTradeDate":"\/Date(1462813200000)\/","TotalRecord":1657},{"ID":2933,"CatID":1,"Exchange":"HOSE","IndustryName1":"Xây dựng và Bất động sản","IndustryName2":"Phát triển bất động sản","IndustryName3":"Phát triển bất động sản","Code":"CIG","Name":"CTCP COMA 18","TotalShares":31539947,"URL":"https://finance.vietstock.vn/CIG-ctcp-coma-18.htm","Row":222,"FirstTradeDate":"\/Date(1311008400000)\/","TotalRecord":1657},{"ID":95,"CatID":1,"Exchange":"HOSE","IndustryName1":"Xây dựng và Bất động sản","IndustryName2":"Xây dựng công nghiệp nặng và dân dụng","IndustryName3":"Xây dựng cầu đường, đường cao tốc","Code":"CII","Name":"CTCP Đầu tư Hạ tầng Kỹ thuật Thành phố Hồ Chí Minh","TotalShares":283168152,"URL":"https://finance.vietstock.vn/CII-ctcp-dau-tu-ha-tang-ky-thuat-thanh-pho-ho-chi-minh.htm","Row":223,"FirstTradeDate":"\/Date(1147885200000)\/","TotalRecord":1657},{"ID":2922,"CatID":5,"Exchange":"UPCoM","IndustryName1":"Xây dựng và Bất động sản","IndustryName2":"Xây dựng công nghiệp nặng và dân dụng","IndustryName3":"Xây dựng công nghiệp nặng và dân dụng khác","Code":"CIP","Name":"CTCP Xây lắp và Sản xuất Công nghiệp","TotalShares":4545000,"URL":"https://finance.vietstock.vn/CIP-ctcp-xay-lap-va-san-xuat-cong-nghiep.htm","Row":224,"FirstTradeDate":"\/Date(1506445200000)\/","TotalRecord":1657},{"ID":900,"CatID":2,"Exchange":"HNX","IndustryName1":"Sản xuất","IndustryName2":"Sản xuất thiết bị, máy móc","IndustryName3":"Sản xuất động cơ, tua bin và thiết bị truyền tải điện","Code":"CJC","Name":"CTCP Cơ điện Miền Trung","TotalShares":4000000,"URL":"https://finance.vietstock.vn/CJC-ctcp-co-dien-mien-trung.htm","Row":225,"FirstTradeDate":"\/Date(1166029200000)\/","TotalRecord":1657},{"ID":4711,"CatID":5,"Exchange":"UPCoM","IndustryName1":"Sản xuất","IndustryName2":"Sản xuất sản phẩm kim loại tổng hợp","IndustryName3":"Sản xuất sản phẩm kim loại tổng hợp khác","Code":"CKA","Name":"CTCP Cơ Khí An Giang","TotalShares":3286404,"URL":"https://finance.vietstock.vn/CKA-ctcp-co-khi-an-giang.htm","Row":226,"FirstTradeDate":"\/Date(1539709200000)\/","TotalRecord":1657},{"ID":3620,"CatID":5,"Exchange":"UPCoM","IndustryName1":"Sản xuất","IndustryName2":"Sản xuất sản phẩm kim loại tổng hợp","IndustryName3":"Sản xuất kiến trúc và kết cấu kim loại","Code":"CKD","Name":"CTCP Cơ khí Đông Anh LICOGI","TotalShares":31000000,"URL":"https://finance.vietstock.vn/CKD-ctcp-co-khi-dong-anh-licogi.htm","Row":227,"FirstTradeDate":"\/Date(1432141200000)\/","TotalRecord":1657},{"ID":2239,"CatID":1,"Exchange":"HOSE","IndustryName1":"Xây dựng và Bất động sản","IndustryName2":"Phát triển bất động sản","IndustryName3":"Phát triển bất động sản","Code":"CKG","Name":"CTCP Tập đoàn Tư vấn Đầu tư Xây dựng Kiên Giang","TotalShares":82499781,"URL":"https://finance.vietstock.vn/CKG-ctcp-tap-doan-tu-van-dau-tu-xay-dung-kien-giang.htm","Row":228,"FirstTradeDate":"\/Date(1585069200000)\/","TotalRecord":1657},{"ID":2175,"CatID":2,"Exchange":"HNX","IndustryName1":"Bán buôn","IndustryName2":"Bán buôn hàng lâu bền","IndustryName3":"Bán buôn máy móc, thiết bị và vật tư","Code":"CKV","Name":"CTCP COKYVINA","TotalShares":4050000,"URL":"https://finance.vietstock.vn/CKV-ctcp-cokyvina.htm","Row":229,"FirstTradeDate":"\/Date(1268240400000)\/","TotalRecord":1657},{"ID":779,"CatID":1,"Exchange":"HOSE","IndustryName1":"Sản xuất","IndustryName2":"Sản xuất đồ uống và thuốc lá","IndustryName3":"Sản xuất thuốc lá","Code":"CLC","Name":"CTCP Cát Lợi","TotalShares":26207583,"URL":"https://finance.vietstock.vn/CLC-ctcp-cat-loi.htm","Row":230,"FirstTradeDate":"\/Date(1163610000000)\/","TotalRecord":1657},{"ID":2252,"CatID":5,"Exchange":"UPCoM","IndustryName1":"Xây dựng và Bất động sản","IndustryName2":"Xây dựng nhà cửa, cao ốc","IndustryName3":"Xây dựng nhà ở, khu dân cư, cao ốc","Code":"CLG","Name":"CTCP Đầu tư và Phát triển Nhà đất COTEC","TotalShares":21150000,"URL":"https://finance.vietstock.vn/CLG-ctcp-dau-tu-va-phat-trien-nha-dat-cotec.htm","Row":231,"FirstTradeDate":"\/Date(1620147600000)\/","TotalRecord":1657},{"ID":2153,"CatID":2,"Exchange":"HNX","IndustryName1":"Sản xuất","IndustryName2":"Sản xuất sản phẩm khoáng chất phi kim","IndustryName3":"Sản xuất xi măng và các sản phẩm bê tông","Code":"CLH","Name":"CTCP Xi măng La Hiên VVMI","TotalShares":12000000,"URL":"https://finance.vietstock.vn/CLH-ctcp-xi-mang-la-hien-vvmi.htm","Row":232,"FirstTradeDate":"\/Date(1465232400000)\/","TotalRecord":1657},{"ID":1637,"CatID":1,"Exchange":"HOSE","IndustryName1":"Vận tải và kho bãi","IndustryName2":"Hỗ trợ vận tải","IndustryName3":"Hoạt động hỗ trợ vận tải đường thủy","Code":"CLL","Name":"CTCP Cảng Cát Lái","TotalShares":34000000,"URL":"https://finance.vietstock.vn/CLL-ctcp-cang-cat-lai.htm","Row":233,"FirstTradeDate":"\/Date(1404752400000)\/","TotalRecord":1657},{"ID":2221,"CatID":2,"Exchange":"HNX","IndustryName1":"Bán buôn","IndustryName2":"Bán buôn hàng lâu bền","IndustryName3":"Bán buôn kim loại và khoáng sản (trừ dầu khí)","Code":"CLM","Name":"CTCP Xuất nhập khẩu Than - Vinacomin","TotalShares":11000000,"URL":"https://finance.vietstock.vn/CLM-ctcp-xuat-nhap-khau-than-vinacomin.htm","Row":234,"FirstTradeDate":"\/Date(1460653200000)\/","TotalRecord":1657},{"ID":1918,"CatID":1,"Exchange":"HOSE","IndustryName1":"Tiện ích","IndustryName2":"Nước, chất thải và các hệ thống khác","IndustryName3":"Hệ thống thủy lợi và cung cấp nước","Code":"CLW","Name":"CTCP Cấp nước Chợ Lớn","TotalShares":13000000,"URL":"https://finance.vietstock.vn/CLW-ctcp-cap-nuoc-cho-lon.htm","Row":235,"FirstTradeDate":"\/Date(1294678800000)\/","TotalRecord":1657},{"ID":4252,"CatID":5,"Exchange":"UPCoM","IndustryName1":"Bán buôn","IndustryName2":"Bán buôn hàng tiêu dùng","IndustryName3":"Bán buôn thực phẩm, tạp hóa và các sản phẩm có liên quan","Code":"CLX","Name":"CTCP Xuất nhập khẩu và Đầu tư Chợ Lớn (CHOLIMEX)","TotalShares":86600000,"URL":"https://finance.vietstock.vn/CLX-ctcp-xuat-nhap-khau-va-dau-tu-cho-lon-cholimex.htm","Row":236,"FirstTradeDate":"\/Date(1488301200000)\/","TotalRecord":1657},{"ID":901,"CatID":2,"Exchange":"HNX","IndustryName1":"Bán buôn","IndustryName2":"Bán buôn hàng lâu bền","IndustryName3":"Bán buôn máy móc, thiết bị và vật tư","Code":"CMC","Name":"CTCP Đầu tư CMC","TotalShares":4561050,"URL":"https://finance.vietstock.vn/CMC-ctcp-dau-tu-cmc.htm","Row":237,"FirstTradeDate":"\/Date(1165770000000)\/","TotalRecord":1657},{"ID":1247,"CatID":5,"Exchange":"UPCoM","IndustryName1":"Bán buôn","IndustryName2":"Bán buôn hàng lâu bền","IndustryName3":"Bán buôn gỗ xẻ và vật liệu xây dựng khác","Code":"CMD","Name":"CTCP Vật liệu Xây dựng và Trang trí nội thất Thành phố Hồ Chí Minh","TotalShares":15000000,"URL":"https://finance.vietstock.vn/CMD-ctcp-vat-lieu-xay-dung-va-trang-tri-noi-that-thanh-pho-ho-chi-minh.htm","Row":238,"FirstTradeDate":"\/Date(1562259600000)\/","TotalRecord":1657},{"ID":2312,"CatID":5,"Exchange":"UPCoM","IndustryName1":"Sản xuất","IndustryName2":"Sản xuất thực phẩm","IndustryName3":"Sản xuất các loại thực phẩm khác","Code":"CMF","Name":"CTCP Thực phẩm Cholimex","TotalShares":8100000,"URL":"https://finance.vietstock.vn/CMF-ctcp-thuc-pham-cholimex.htm","Row":239,"FirstTradeDate":"\/Date(1480438800000)\/","TotalRecord":1657},{"ID":1879,"CatID":1,"Exchange":"HOSE","IndustryName1":"Công nghệ và thông tin","IndustryName2":"Các dịch vụ thông tin khác","IndustryName3":"Các dịch vụ thông tin khác","Code":"CMG","Name":"CTCP Tập đoàn Công nghệ CMC","TotalShares":99999866,"URL":"https://finance.vietstock.vn/CMG-ctcp-tap-doan-cong-nghe-cmc.htm","Row":240,"FirstTradeDate":"\/Date(1264093200000)\/","TotalRecord":1657},{"ID":1860,"CatID":5,"Exchange":"UPCoM","IndustryName1":"Khai khoáng","IndustryName2":"Khai khoáng (ngoại trừ dầu mỏ và khí đốt)","IndustryName3":"Khai thác quặng kim loại","Code":"CMI","Name":"CTCP CMISTONE Việt Nam","TotalShares":15002500,"URL":"https://finance.vietstock.vn/CMI-ctcp-cmistone-viet-nam.htm","Row":241,"FirstTradeDate":"\/Date(1560445200000)\/","TotalRecord":1657},{"ID":3078,"CatID":5,"Exchange":"UPCoM","IndustryName1":"Bán buôn","IndustryName2":"Bán buôn hàng lâu bền","IndustryName3":"Bán buôn máy móc, thiết bị và vật tư","Code":"CMK","Name":"CTCP Cơ khí Mạo Khê - Vinacomin","TotalShares":1432578,"URL":"https://finance.vietstock.vn/CMK-ctcp-co-khi-mao-khe-vinacomin.htm","Row":242,"FirstTradeDate":"\/Date(1445360400000)\/","TotalRecord":1657},{"ID":2161,"CatID":5,"Exchange":"UPCoM","IndustryName1":"Sản xuất","IndustryName2":"Sản xuất thực phẩm","IndustryName3":"Sản xuất các loại thực phẩm khác","Code":"CMN","Name":"CTCP Lương thực Thực phẩm Colusa - Miliket","TotalShares":4800000,"URL":"https://finance.vietstock.vn/CMN-ctcp-luong-thuc-thuc-pham-colusa-miliket.htm","Row":243,"FirstTradeDate":"\/Date(1499619600000)\/","TotalRecord":1657},{"ID":3868,"CatID":5,"Exchange":"UPCoM","IndustryName1":"Vận tải và kho bãi","IndustryName2":"Hỗ trợ vận tải","IndustryName3":"Hoạt động hỗ trợ vận tải đường thủy","Code":"CMP","Name":"CTCP Cảng Chân Mây","TotalShares":32405415,"URL":"https://finance.vietstock.vn/CMP-ctcp-cang-chan-may.htm","Row":244,"FirstTradeDate":"\/Date(1455469200000)\/","TotalRecord":1657},{"ID":2529,"CatID":2,"Exchange":"HNX","IndustryName1":"Xây dựng và Bất động sản","IndustryName2":"Xây dựng công nghiệp nặng và dân dụng","IndustryName3":"Xây dựng hệ thống tiện ích","Code":"CMS","Name":"CTCP CMVIETNAM","TotalShares":17200000,"URL":"https://finance.vietstock.vn/CMS-ctcp-cmvietnam.htm","Row":245,"FirstTradeDate":"\/Date(1290963600000)\/","TotalRecord":1657},{"ID":1897,"CatID":5,"Exchange":"UPCoM","IndustryName1":"Công nghệ và thông tin","IndustryName2":"Viễn thông","IndustryName3":"Các loại hình viễn thông khác","Code":"CMT","Name":"CTCP Công nghệ Mạng và Truyền thông","TotalShares":8000000,"URL":"https://finance.vietstock.vn/CMT-ctcp-cong-nghe-mang-va-truyen-thong.htm","Row":246,"FirstTradeDate":"\/Date(1556038800000)\/","TotalRecord":1657},{"ID":1733,"CatID":1,"Exchange":"HOSE","IndustryName1":"Bán lẻ","IndustryName2":"Của hàng hàng hóa tổng hợp","IndustryName3":"Cửa hàng tổng hợp","Code":"CMV","Name":"CTCP Thương nghiệp Cà Mau","TotalShares":18155868,"URL":"https://finance.vietstock.vn/CMV-ctcp-thuong-nghiep-ca-mau.htm","Row":247,"FirstTradeDate":"\/Date(1277053200000)\/","TotalRecord":1657},{"ID":4478,"CatID":5,"Exchange":"UPCoM","IndustryName1":"Tiện ích","IndustryName2":"Nước, chất thải và các hệ thống khác","IndustryName3":"Hệ thống thủy lợi và cung cấp nước","Code":"CMW","Name":"CTCP Cấp nước Cà Mau","TotalShares":15534900,"URL":"https://finance.vietstock.vn/CMW-ctcp-cap-nuoc-ca-mau.htm","Row":248,"FirstTradeDate":"\/Date(1491757200000)\/","TotalRecord":1657},{"ID":2368,"CatID":1,"Exchange":"HOSE","IndustryName1":"Sản xuất","IndustryName2":"Sản xuất thực phẩm","IndustryName3":"Sơ chế và đóng gói thủy sản","Code":"CMX","Name":"CTCP Camimex Group","TotalShares":30408751,"URL":"https://finance.vietstock.vn/CMX-ctcp-camimex-group.htm","Row":249,"FirstTradeDate":"\/Date(1289235600000)\/","TotalRecord":1657},{"ID":3015,"CatID":5,"Exchange":"UPCoM","IndustryName1":"Bán buôn","IndustryName2":"Bán buôn hàng tiêu dùng","IndustryName3":"Bán buôn các mặt hàng tiêu dùng khác","Code":"CNC","Name":"CTCP Công nghệ Cao Traphaco","TotalShares":11364325,"URL":"https://finance.vietstock.vn/CNC-ctcp-cong-nghe-cao-traphaco.htm","Row":250,"FirstTradeDate":"\/Date(1403629200000)\/","TotalRecord":1657}]