[{"ID":1168,"CatID":2,"Exchange":"HNX","IndustryName":"Khai khoáng (ngoại trừ dầu mỏ và khí đốt)","Code":"TC6","Name":"CTCP Than Cọc Sáu - Vinacomin","TotalShares":32496105,"URL":"https://finance.vietstock.vn/TC6-ctcp-than-coc-sau-vinacomin.htm","Row":1151,"TotalRecord":3172},{"ID":1387,"CatID":2,"Exchange":"HNX","IndustryName":"Khai khoáng (ngoại trừ dầu mỏ và khí đốt)","Code":"TDN","Name":"CTCP Than Đèo Nai - Vinacomin","TotalShares":29439097,"URL":"https://finance.vietstock.vn/TDN-ctcp-than-deo-nai-vinacomin.htm","Row":1152,"TotalRecord":3172},{"ID":1532,"CatID":2,"Exchange":"HNX","IndustryName":"Khai khoáng (ngoại trừ dầu mỏ và khí đốt)","Code":"HLC","Name":"CTCP Than Hà Lầm - Vinacomin","TotalShares":25415199,"URL":"https://finance.vietstock.vn/HLC-ctcp-than-ha-lam-vinacomin.htm","Row":1153,"TotalRecord":3172},{"ID":1414,"CatID":2,"Exchange":"HNX","IndustryName":"Khai khoáng (ngoại trừ dầu mỏ và khí đốt)","Code":"THT","Name":"CTCP Than Hà Tu - Vinacomin","TotalShares":24569052,"URL":"https://finance.vietstock.vn/THT-ctcp-than-ha-tu-vinacomin.htm","Row":1154,"TotalRecord":3172},{"ID":1801,"CatID":2,"Exchange":"HNX","IndustryName":"Khai khoáng (ngoại trừ dầu mỏ và khí đốt)","Code":"MDC","Name":"CTCP Than Mông Dương - Vinacomin","TotalShares":21418346,"URL":"https://finance.vietstock.vn/MDC-ctcp-than-mong-duong-vinacomin.htm","Row":1155,"TotalRecord":3172},{"ID":927,"CatID":2,"Exchange":"HNX","IndustryName":"Khai khoáng (ngoại trừ dầu mỏ và khí đốt)","Code":"NBC","Name":"CTCP Than Núi Béo - Vinacomin","TotalShares":36999124,"URL":"https://finance.vietstock.vn/NBC-ctcp-than-nui-beo-vinacomin.htm","Row":1156,"TotalRecord":3172},{"ID":1718,"CatID":2,"Exchange":"HNX","IndustryName":"Khai khoáng (ngoại trừ dầu mỏ và khí đốt)","Code":"TVD","Name":"CTCP Than Vàng Danh - Vinacomin","TotalShares":44962864,"URL":"https://finance.vietstock.vn/TVD-ctcp-than-vang-danh-vinacomin.htm","Row":1157,"TotalRecord":3172},{"ID":4456,"CatID":5,"Exchange":"UPCoM","IndustryName":"Sản xuất sản phẩm khoáng chất phi kim","Code":"X77","Name":"CTCP Thành An 77","TotalShares":1340877,"URL":"https://finance.vietstock.vn/X77-ctcp-thanh-an-77.htm","Row":1158,"TotalRecord":3172},{"ID":2419,"CatID":2,"Exchange":"HNX","IndustryName":"Bán buôn hàng lâu bền","Code":"THS","Name":"CTCP Thanh Hoa - Sông Đà","TotalShares":3000000,"URL":"https://finance.vietstock.vn/THS-ctcp-thanh-hoa-song-da.htm","Row":1159,"TotalRecord":3172},{"ID":1115,"CatID":1,"Exchange":"HOSE","IndustryName":"Sản xuất thực phẩm","Code":"SBT","Name":"CTCP Thành Thành Công - Biên Hòa","TotalShares":617158147,"URL":"https://finance.vietstock.vn/SBT-ctcp-thanh-thanh-cong-bien-hoa.htm","Row":1160,"TotalRecord":3172},{"ID":4086,"CatID":1,"Exchange":"HOSE","IndustryName":"Bán buôn hàng lâu bền","Code":"DGW","Name":"CTCP Thế Giới Số","TotalShares":43151747,"URL":"https://finance.vietstock.vn/DGW-ctcp-the-gioi-so.htm","Row":1161,"TotalRecord":3172},{"ID":1734,"CatID":5,"Exchange":"UPCoM","IndustryName":"Cửa hàng thiết bị điện tử gia đình","Code":"TAG","Name":"CTCP Thế Giới Số Trần Anh","TotalShares":24914991,"URL":"https://finance.vietstock.vn/TAG-ctcp-the-gioi-so-tran-anh.htm","Row":1162,"TotalRecord":3172},{"ID":2003,"CatID":5,"Exchange":"UPCoM","IndustryName":"Phát triển bất động sản","Code":"C21","Name":"CTCP Thế Kỷ 21 ","TotalShares":19336371,"URL":"https://finance.vietstock.vn/C21-ctcp-the-ky-21.htm","Row":1163,"TotalRecord":3172},{"ID":2261,"CatID":5,"Exchange":"UPCoM","IndustryName":"Sản xuất các sản phẩm nhựa và cao su","Code":"GER","Name":"CTCP Thể thao Ngôi sao Geru","TotalShares":2200000,"URL":"https://finance.vietstock.vn/GER-ctcp-the-thao-ngoi-sao-geru.htm","Row":1164,"TotalRecord":3172},{"ID":2537,"CatID":5,"Exchange":"UPCoM","IndustryName":"Sản xuất các sản phẩm kim loại cơ bản","Code":"DNS","Name":"CTCP Thép Đà Nẵng","TotalShares":21600000,"URL":"https://finance.vietstock.vn/DNS-ctcp-thep-da-nang.htm","Row":1165,"TotalRecord":3172},{"ID":2546,"CatID":5,"Exchange":"UPCoM","IndustryName":"Sản xuất các sản phẩm kim loại cơ bản","Code":"DNY","Name":"CTCP Thép DANA - Ý","TotalShares":26999517,"URL":"https://finance.vietstock.vn/DNY-ctcp-thep-dana-y.htm","Row":1166,"TotalRecord":3172},{"ID":4518,"CatID":2,"Exchange":"HNX","IndustryName":"Bán buôn hàng lâu bền","Code":"MEL","Name":"CTCP Thép Mê Lin","TotalShares":15000000,"URL":"https://finance.vietstock.vn/MEL-ctcp-thep-me-lin.htm","Row":1167,"TotalRecord":3172},{"ID":2684,"CatID":1,"Exchange":"HOSE","IndustryName":"Sản xuất các sản phẩm kim loại cơ bản","Code":"NKG","Name":"CTCP Thép Nam Kim","TotalShares":181999868,"URL":"https://finance.vietstock.vn/NKG-ctcp-thep-nam-kim.htm","Row":1168,"TotalRecord":3172},{"ID":1728,"CatID":5,"Exchange":"UPCoM","IndustryName":"Sản xuất các sản phẩm kim loại cơ bản","Code":"TNB","Name":"CTCP Thép Nhà Bè - VNSTEEL","TotalShares":11500000,"URL":"https://finance.vietstock.vn/TNB-ctcp-thep-nha-be-vnsteel.htm","Row":1169,"TotalRecord":3172},{"ID":2415,"CatID":1,"Exchange":"HOSE","IndustryName":"Sản xuất các sản phẩm kim loại cơ bản","Code":"POM","Name":"CTCP Thép Pomina","TotalShares":279676336,"URL":"https://finance.vietstock.vn/POM-ctcp-thep-pomina.htm","Row":1170,"TotalRecord":3172},{"ID":2956,"CatID":5,"Exchange":"UPCoM","IndustryName":"Sản xuất các sản phẩm kim loại cơ bản","Code":"TNS","Name":"CTCP Thép tấm lá Thống Nhất","TotalShares":20000000,"URL":"https://finance.vietstock.vn/TNS-ctcp-thep-tam-la-thong-nhat.htm","Row":1171,"TotalRecord":3172},{"ID":2518,"CatID":5,"Exchange":"UPCoM","IndustryName":"Sản xuất các sản phẩm kim loại cơ bản","Code":"TDS","Name":"CTCP Thép Thủ Đức - VNSTEEL","TotalShares":12225393,"URL":"https://finance.vietstock.vn/TDS-ctcp-thep-thu-duc-vnsteel.htm","Row":1172,"TotalRecord":3172},{"ID":1727,"CatID":1,"Exchange":"HOSE","IndustryName":"Sản xuất các sản phẩm kim loại cơ bản","Code":"VCA","Name":"CTCP Thép VICASA - VNSTEEL","TotalShares":15187322,"URL":"https://finance.vietstock.vn/VCA-ctcp-thep-vicasa-vnsteel.htm","Row":1173,"TotalRecord":3172},{"ID":834,"CatID":1,"Exchange":"HOSE","IndustryName":"Sản xuất các sản phẩm kim loại cơ bản","Code":"VIS","Name":"CTCP Thép Việt Ý","TotalShares":73830393,"URL":"https://finance.vietstock.vn/VIS-ctcp-thep-viet-y.htm","Row":1174,"TotalRecord":3172},{"ID":3686,"CatID":5,"Exchange":"UPCoM","IndustryName":"Bất động sản ","Code":"MA1","Name":"CTCP Thiết bị","TotalShares":5289715,"URL":"https://finance.vietstock.vn/MA1-ctcp-thiet-bi.htm","Row":1175,"TotalRecord":3172},{"ID":935,"CatID":2,"Exchange":"HNX","IndustryName":"Sản xuất các sản phẩm điện tử, vi tính","Code":"POT","Name":"CTCP Thiết bị Bưu điện","TotalShares":19430006,"URL":"https://finance.vietstock.vn/POT-ctcp-thiet-bi-buu-dien.htm","Row":1176,"TotalRecord":3172},{"ID":2137,"CatID":1,"Exchange":"HOSE","IndustryName":"Sản xuất thiết bị, máy móc","Code":"THI","Name":"CTCP Thiết bị Điện","TotalShares":48800000,"URL":"https://finance.vietstock.vn/THI-ctcp-thiet-bi-dien.htm","Row":1177,"TotalRecord":3172},{"ID":2862,"CatID":5,"Exchange":"UPCoM","IndustryName":"Sản xuất thiết bị, máy móc","Code":"EMG","Name":"CTCP Thiết bị Phụ Tùng Cơ Điện","TotalShares":3000000,"URL":"https://finance.vietstock.vn/EMG-ctcp-thiet-bi-phu-tung-co-dien.htm","Row":1178,"TotalRecord":3172},{"ID":2624,"CatID":1,"Exchange":"HOSE","IndustryName":"Bán buôn hàng lâu bền","Code":"SMA","Name":"CTCP Thiết bị Phụ tùng Sài Gòn","TotalShares":20352836,"URL":"https://finance.vietstock.vn/SMA-ctcp-thiet-bi-phu-tung-sai-gon.htm","Row":1179,"TotalRecord":3172},{"ID":1724,"CatID":5,"Exchange":"UPCoM","IndustryName":"Cửa hàng đồ nội thất và đồ dùng gia đình","Code":"PEQ","Name":"CTCP Thiết bị Xăng dầu Petrolimex","TotalShares":4965514,"URL":"https://finance.vietstock.vn/PEQ-ctcp-thiet-bi-xang-dau-petrolimex.htm","Row":1180,"TotalRecord":3172},{"ID":2757,"CatID":1,"Exchange":"HOSE","IndustryName":"Bán buôn hàng lâu bền","Code":"JVC","Name":"CTCP Thiết bị Y tế Việt Nhật","TotalShares":112500171,"URL":"https://finance.vietstock.vn/JVC-ctcp-thiet-bi-y-te-viet-nhat.htm","Row":1181,"TotalRecord":3172},{"ID":2019,"CatID":2,"Exchange":"HNX","IndustryName":"Xây dựng nhà cửa, cao ốc","Code":"PTD","Name":"CTCP Thiết kế Xây dựng Thương mại Phúc Thịnh","TotalShares":3200000,"URL":"https://finance.vietstock.vn/PTD-ctcp-thiet-ke-xay-dung-thuong-mai-phuc-thinh.htm","Row":1182,"TotalRecord":3172},{"ID":1561,"CatID":2,"Exchange":"HNX","IndustryName":"Bất động sản ","Code":"BAX","Name":"CTCP Thống Nhất","TotalShares":8200000,"URL":"https://finance.vietstock.vn/BAX-ctcp-tho´ng-nha´t.htm","Row":1183,"TotalRecord":3172},{"ID":3334,"CatID":5,"Exchange":"UPCoM","IndustryName":"Sản xuất các sản phẩm gỗ","Code":"TQN","Name":"CTCP Thông Quảng Ninh","TotalShares":3600000,"URL":"https://finance.vietstock.vn/TQN-ctcp-thong-quang-ninh.htm","Row":1184,"TotalRecord":3172},{"ID":4490,"CatID":5,"Exchange":"UPCoM","IndustryName":"Hỗ trợ vận tải","Code":"TSG","Name":"CTCP Thông tin Tín hiệu Đường sắt Sài Gòn","TotalShares":3074100,"URL":"https://finance.vietstock.vn/TSG-ctcp-thong-tin-tin-hieu-duong-sat-sai-gon.htm","Row":1185,"TotalRecord":3172},{"ID":4716,"CatID":1,"Exchange":"HOSE","IndustryName":"Sản xuất các sản phẩm nhựa và cao su","Code":"TDP","Name":"CTCP Thuận Đức","TotalShares":53759837,"URL":"https://finance.vietstock.vn/TDP-ctcp-thuan-duc.htm","Row":1186,"TotalRecord":3172},{"ID":2629,"CatID":5,"Exchange":"UPCoM","IndustryName":"Vận tải trung chuyển và vận tải hành khách bằng đường bộ","Code":"GTT","Name":"CTCP Thuận Thảo","TotalShares":43503000,"URL":"https://finance.vietstock.vn/GTT-ctcp-thuan-thao.htm","Row":1187,"TotalRecord":3172},{"ID":2727,"CatID":2,"Exchange":"HNX","IndustryName":"Sản xuất thực phẩm","Code":"BCF","Name":"CTCP Thực phẩm Bích Chi","TotalShares":21083725,"URL":"https://finance.vietstock.vn/BCF-ctcp-thuc-pham-bich-chi.htm","Row":1188,"TotalRecord":3172},{"ID":2312,"CatID":5,"Exchange":"UPCoM","IndustryName":"Sản xuất thực phẩm","Code":"CMF","Name":"CTCP Thực phẩm Cholimex","TotalShares":8100000,"URL":"https://finance.vietstock.vn/CMF-ctcp-thuc-pham-cholimex.htm","Row":1189,"TotalRecord":3172},{"ID":2108,"CatID":5,"Exchange":"UPCoM","IndustryName":"Bán buôn hàng tiêu dùng","Code":"IFC","Name":"CTCP Thực phẩm Công nghệ Sài Gòn","TotalShares":9000000,"URL":"https://finance.vietstock.vn/IFC-ctcp-thuc-pham-cong-nghe-sai-gon.htm","Row":1190,"TotalRecord":3172},{"ID":3884,"CatID":5,"Exchange":"UPCoM","IndustryName":"Sản xuất thực phẩm","Code":"HAF","Name":"CTCP Thực phẩm Hà Nội","TotalShares":14500000,"URL":"https://finance.vietstock.vn/HAF-ctcp-thuc-pham-ha-noi.htm","Row":1191,"TotalRecord":3172},{"ID":2285,"CatID":5,"Exchange":"UPCoM","IndustryName":"Sản xuất thực phẩm","Code":"HNF","Name":"CTCP Thực phẩm Hữu Nghị","TotalShares":30000000,"URL":"https://finance.vietstock.vn/HNF-ctcp-thuc-pham-huu-nghi.htm","Row":1192,"TotalRecord":3172},{"ID":1106,"CatID":2,"Exchange":"HNX","IndustryName":"Sản xuất đồ uống và thuốc lá","Code":"VDL","Name":"CTCP Thực phẩm Lâm Đồng","TotalShares":14657150,"URL":"https://finance.vietstock.vn/VDL-ctcp-thuc-pham-lam-dong.htm","Row":1193,"TotalRecord":3172},{"ID":1245,"CatID":5,"Exchange":"UPCoM","IndustryName":"Sản xuất thực phẩm","Code":"AGX","Name":"CTCP Thực phẩm Nông Sản xuất khẩu Sài Gòn","TotalShares":10800000,"URL":"https://finance.vietstock.vn/AGX-ctcp-thuc-pham-nong-san-xuat-khau-sai-gon.htm","Row":1194,"TotalRecord":3172},{"ID":780,"CatID":5,"Exchange":"UPCoM","IndustryName":"Bán buôn hàng tiêu dùng","Code":"IFS","Name":"CTCP Thực phẩm Quốc tế","TotalShares":87140984,"URL":"https://finance.vietstock.vn/IFS-ctcp-thuc-pham-quoc-te.htm","Row":1195,"TotalRecord":3172},{"ID":793,"CatID":1,"Exchange":"HOSE","IndustryName":"Sản xuất thực phẩm","Code":"FMC","Name":"CTCP Thực phẩm Sao Ta","TotalShares":58850000,"URL":"https://finance.vietstock.vn/FMC-ctcp-thuc-pham-sao-ta.htm","Row":1196,"TotalRecord":3172},{"ID":1841,"CatID":2,"Exchange":"HNX","IndustryName":"Sản xuất hóa chất, dược phẩm","Code":"CPC","Name":"CTCP Thuốc sát trùng Cần Thơ","TotalShares":4303050,"URL":"https://finance.vietstock.vn/CPC-ctcp-thuoc-sat-trung-can-tho.htm","Row":1197,"TotalRecord":3172},{"ID":1726,"CatID":1,"Exchange":"HOSE","IndustryName":"Sản xuất hóa chất, dược phẩm","Code":"VPS","Name":"CTCP Thuốc sát trùng Việt Nam (VIPESCO)","TotalShares":24460792,"URL":"https://finance.vietstock.vn/VPS-ctcp-thuoc-sat-trung-viet-nam-vipesco.htm","Row":1198,"TotalRecord":3172},{"ID":2759,"CatID":5,"Exchange":"UPCoM","IndustryName":"Sản xuất hóa chất, dược phẩm","Code":"VNY","Name":"CTCP Thuốc thú y Trung ương I","TotalShares":8250000,"URL":"https://finance.vietstock.vn/VNY-ctcp-thuoc-thu-y-trung-uong-i.htm","Row":1199,"TotalRecord":3172},{"ID":4614,"CatID":5,"Exchange":"UPCoM","IndustryName":"Sản xuất hóa chất, dược phẩm","Code":"VET","Name":"CTCP Thuốc thú y Trung ương Navetco","TotalShares":16000000,"URL":"https://finance.vietstock.vn/VET-ctcp-thuoc-thu-y-trung-uong-navetco.htm","Row":1200,"TotalRecord":3172}]