[{"ID":2469,"CatID":5,"Exchange":"UPCoM","IndustryName":"Sản xuất sản phẩm khoáng chất phi kim","Code":"XMD","Name":"CTCP Xuân Mai - Đạo Tú","TotalShares":4000000,"URL":"https://finance.vietstock.vn/XMD-ctcp-xuan-mai-dao-tu.htm","Row":1501,"TotalRecord":3172},{"ID":1935,"CatID":1,"Exchange":"HOSE","IndustryName":"Sản xuất thực phẩm","Code":"AGM","Name":"CTCP Xuất nhập khẩu An Giang","TotalShares":18200000,"URL":"https://finance.vietstock.vn/AGM-ctcp-xuat-nhap-khau-an-giang.htm","Row":1502,"TotalRecord":3172},{"ID":1756,"CatID":2,"Exchange":"HNX","IndustryName":"Bán buôn hàng lâu bền","Code":"ARM","Name":"CTCP Xuất nhập khẩu Hàng không","TotalShares":3111283,"URL":"https://finance.vietstock.vn/ARM-ctcp-xuat-nhap-khau-hang-khong.htm","Row":1503,"TotalRecord":3172},{"ID":4307,"CatID":5,"Exchange":"UPCoM","IndustryName":"Sản xuất thực phẩm","Code":"KGM","Name":"CTCP Xuất nhập khẩu Kiên Giang","TotalShares":25430000,"URL":"https://finance.vietstock.vn/KGM-ctcp-xuat-nhap-khau-kien-giang.htm","Row":1504,"TotalRecord":3172},{"ID":2390,"CatID":5,"Exchange":"UPCoM","IndustryName":"Sản xuất thực phẩm","Code":"FHN","Name":"CTCP Xuất nhập khẩu Lương thực Thực phẩm Hà Nội","TotalShares":3000000,"URL":"https://finance.vietstock.vn/FHN-ctcp-xuat-nhap-khau-luong-thuc-thuc-pham-ha-noi.htm","Row":1505,"TotalRecord":3172},{"ID":3218,"CatID":5,"Exchange":"UPCoM","IndustryName":"Sản xuất thực phẩm","Code":"AFX","Name":"CTCP Xuất nhập khẩu Nông sản Thực phẩm An Giang","TotalShares":35000000,"URL":"https://finance.vietstock.vn/AFX-ctcp-xuat-nhap-khau-nong-san-thuc-pham-an-giang.htm","Row":1506,"TotalRecord":3172},{"ID":1079,"CatID":1,"Exchange":"HOSE","IndustryName":"Bán buôn hàng tiêu dùng","Code":"PIT","Name":"CTCP Xuất nhập khẩu Petrolimex","TotalShares":15199345,"URL":"https://finance.vietstock.vn/PIT-ctcp-xuat-nhap-khau-petrolimex.htm","Row":1507,"TotalRecord":3172},{"ID":3758,"CatID":1,"Exchange":"HOSE","IndustryName":"Bán buôn hàng tiêu dùng","Code":"QBS","Name":"CTCP Xuất nhập khẩu Quảng Bình","TotalShares":69329928,"URL":"https://finance.vietstock.vn/QBS-ctcp-xuat-nhap-khau-quang-binh.htm","Row":1508,"TotalRecord":3172},{"ID":736,"CatID":2,"Exchange":"HNX","IndustryName":"Sản xuất thực phẩm","Code":"SGC","Name":"CTCP Xuất nhập khẩu Sa Giang","TotalShares":7147580,"URL":"https://finance.vietstock.vn/SGC-ctcp-xuat-nhap-khau-sa-giang.htm","Row":1509,"TotalRecord":3172},{"ID":2221,"CatID":2,"Exchange":"HNX","IndustryName":"Bán buôn hàng lâu bền","Code":"CLM","Name":"CTCP Xuất nhập khẩu Than - Vinacomin","TotalShares":11000000,"URL":"https://finance.vietstock.vn/CLM-ctcp-xuat-nhap-khau-than-vinacomin.htm","Row":1510,"TotalRecord":3172},{"ID":38,"CatID":5,"Exchange":"UPCoM","IndustryName":"Sản xuất thực phẩm","Code":"AGF","Name":"CTCP Xuất nhập khẩu Thủy sản An Giang","TotalShares":28109743,"URL":"https://finance.vietstock.vn/AGF-ctcp-xuat-nhap-khau-thuy-san-an-giang.htm","Row":1511,"TotalRecord":3172},{"ID":783,"CatID":1,"Exchange":"HOSE","IndustryName":"Sản xuất thực phẩm","Code":"ABT","Name":"CTCP Xuất nhập khẩu Thủy sản Bến Tre","TotalShares":14107207,"URL":"https://finance.vietstock.vn/ABT-ctcp-xuat-nhap-khau-thuy-san-ben-tre.htm","Row":1512,"TotalRecord":3172},{"ID":3004,"CatID":5,"Exchange":"UPCoM","IndustryName":"Sản xuất thực phẩm","Code":"CCA","Name":"CTCP Xuất nhập khẩu Thuỷ sản Cần Thơ","TotalShares":15092326,"URL":"https://finance.vietstock.vn/CCA-ctcp-xuat-nhap-khau-thuy-san-can-tho.htm","Row":1513,"TotalRecord":3172},{"ID":936,"CatID":1,"Exchange":"HOSE","IndustryName":"Sản xuất thực phẩm","Code":"ACL","Name":"CTCP Xuất nhập khẩu Thủy sản Cửu Long An Giang","TotalShares":50159019,"URL":"https://finance.vietstock.vn/ACL-ctcp-xuat-nhap-khau-thuy-san-cuu-long-an-giang.htm","Row":1514,"TotalRecord":3172},{"ID":2232,"CatID":5,"Exchange":"UPCoM","IndustryName":"Sản xuất thực phẩm","Code":"SPH","Name":"CTCP Xuất nhập khẩu Thủy sản Hà Nội","TotalShares":10000000,"URL":"https://finance.vietstock.vn/SPH-ctcp-xuat-nhap-khau-thuy-san-ha-noi.htm","Row":1515,"TotalRecord":3172},{"ID":2000,"CatID":5,"Exchange":"UPCoM","IndustryName":"Sản xuất thực phẩm","Code":"SPD","Name":"CTCP Xuất nhập khẩu Thủy sản Miền Trung","TotalShares":12000000,"URL":"https://finance.vietstock.vn/SPD-ctcp-xuat-nhap-khau-thuy-san-mien-trung.htm","Row":1516,"TotalRecord":3172},{"ID":2447,"CatID":5,"Exchange":"UPCoM","IndustryName":"Sản xuất thực phẩm","Code":"SNC","Name":"CTCP Xuất nhập khẩu Thủy sản Năm Căn","TotalShares":5000000,"URL":"https://finance.vietstock.vn/SNC-ctcp-xuat-nhap-khau-thuy-san-nam-can.htm","Row":1517,"TotalRecord":3172},{"ID":2078,"CatID":5,"Exchange":"UPCoM","IndustryName":"Sản xuất thực phẩm","Code":"SSN","Name":"CTCP Xuất nhập khẩu Thủy sản Sài Gòn","TotalShares":39600000,"URL":"https://finance.vietstock.vn/SSN-ctcp-xuat-nhap-khau-thuy-san-sai-gon.htm","Row":1518,"TotalRecord":3172},{"ID":1262,"CatID":5,"Exchange":"UPCoM","IndustryName":"Bán buôn hàng tiêu dùng","Code":"TH1","Name":"CTCP Xuất nhập khẩu tổng hợp 1 Việt Nam","TotalShares":13539267,"URL":"https://finance.vietstock.vn/TH1-ctcp-xuat-nhap-khau-tong-hop-1-viet-nam.htm","Row":1519,"TotalRecord":3172},{"ID":4252,"CatID":5,"Exchange":"UPCoM","IndustryName":"Bán buôn hàng tiêu dùng","Code":"CLX","Name":"CTCP Xuất nhập khẩu và Đầu tư Chợ Lớn (CHOLIMEX)","TotalShares":86600000,"URL":"https://finance.vietstock.vn/CLX-ctcp-xuat-nhap-khau-va-dau-tu-cho-lon-cholimex.htm","Row":1520,"TotalRecord":3172},{"ID":1845,"CatID":5,"Exchange":"UPCoM","IndustryName":"Xây dựng công nghiệp nặng và dân dụng","Code":"TNM","Name":"CTCP Xuất nhập khẩu và Xây dựng Công trình","TotalShares":5800000,"URL":"https://finance.vietstock.vn/TNM-ctcp-xuat-nhap-khau-va-xay-dung-cong-trinh.htm","Row":1521,"TotalRecord":3172},{"ID":788,"CatID":1,"Exchange":"HOSE","IndustryName":"Sản xuất hóa chất, dược phẩm","Code":"DMC","Name":"CTCP Xuất nhập khẩu Y Tế Domesco","TotalShares":34727465,"URL":"https://finance.vietstock.vn/DMC-ctcp-xuat-nhap-khau-y-te-domesco.htm","Row":1522,"TotalRecord":3172},{"ID":2008,"CatID":5,"Exchange":"UPCoM","IndustryName":"Bán buôn hàng tiêu dùng","Code":"YTC","Name":"CTCP Xuất nhập khẩu Y tế Thành phố Hồ Chí Minh","TotalShares":3080000,"URL":"https://finance.vietstock.vn/YTC-ctcp-xuat-nhap-khau-y-te-thanh-pho-ho-chi-minh.htm","Row":1523,"TotalRecord":3172},{"ID":2235,"CatID":1,"Exchange":"HOSE","IndustryName":"Bán buôn hàng tiêu dùng","Code":"VMD","Name":"CTCP Y Dược phẩm Vimedimex","TotalShares":15440268,"URL":"https://finance.vietstock.vn/VMD-ctcp-y-duoc-pham-vimedimex.htm","Row":1524,"TotalRecord":3172},{"ID":885,"CatID":1,"Exchange":"HOSE","IndustryName":"Trung gian tín dụng và các hoạt động liên quan","Code":"ACB","Name":"Ngân hàng TMCP Á Châu","TotalShares":2161558460,"URL":"https://finance.vietstock.vn/ACB-ngan-hang-tmcp-a-chau.htm","Row":1525,"TotalRecord":3172},{"ID":1196,"CatID":5,"Exchange":"UPCoM","IndustryName":"Trung gian tín dụng và các hoạt động liên quan","Code":"ABB","Name":"Ngân hàng TMCP An Bình","TotalShares":571311355,"URL":"https://finance.vietstock.vn/ABB-ngan-hang-tmcp-an-binh.htm","Row":1526,"TotalRecord":3172},{"ID":1191,"CatID":2,"Exchange":"HNX","IndustryName":"Trung gian tín dụng và các hoạt động liên quan","Code":"BAB","Name":"Ngân hàng TMCP Bắc Á","TotalShares":708500000,"URL":"https://finance.vietstock.vn/BAB-ngan-hang-tmcp-bac-a.htm","Row":1527,"TotalRecord":3172},{"ID":1197,"CatID":5,"Exchange":"UPCoM","IndustryName":"Trung gian tín dụng và các hoạt động liên quan","Code":"BVB","Name":"Ngân hàng TMCP Bản Việt","TotalShares":367090000,"URL":"https://finance.vietstock.vn/BVB-ngan-hang-tmcp-ban-viet.htm","Row":1528,"TotalRecord":3172},{"ID":1988,"CatID":1,"Exchange":"HOSE","IndustryName":"Trung gian tín dụng và các hoạt động liên quan","Code":"LPB","Name":"Ngân hàng TMCP Bưu điện Liên Việt","TotalShares":1074638915,"URL":"https://finance.vietstock.vn/LPB-ngan-hang-tmcp-buu-dien-lien-viet.htm","Row":1529,"TotalRecord":3172},{"ID":1160,"CatID":1,"Exchange":"HOSE","IndustryName":"Trung gian tín dụng và các hoạt động liên quan","Code":"CTG","Name":"Ngân hàng TMCP Công Thương Việt Nam","TotalShares":3723404556,"URL":"https://finance.vietstock.vn/CTG-ngan-hang-tmcp-cong-thuong-viet-nam.htm","Row":1530,"TotalRecord":3172},{"ID":1161,"CatID":1,"Exchange":"HOSE","IndustryName":"Trung gian tín dụng và các hoạt động liên quan","Code":"BID","Name":"Ngân hàng TMCP Đầu tư và Phát triển Việt Nam","TotalShares":4022018040,"URL":"https://finance.vietstock.vn/BID-ngan-hang-tmcp-dau-tu-va-phat-trien-viet-nam.htm","Row":1531,"TotalRecord":3172},{"ID":1193,"CatID":1,"Exchange":"HOSE","IndustryName":"Trung gian tín dụng và các hoạt động liên quan","Code":"SSB","Name":"Ngân hàng TMCP Đông Nam Á","TotalShares":1208744208,"URL":"https://finance.vietstock.vn/SSB-ngan-hang-tmcp-dong-nam-a.htm","Row":1532,"TotalRecord":3172},{"ID":1166,"CatID":1,"Exchange":"HOSE","IndustryName":"Trung gian tín dụng và các hoạt động liên quan","Code":"MSB","Name":"Ngân hàng TMCP Hàng hải Việt Nam","TotalShares":1175000000,"URL":"https://finance.vietstock.vn/MSB-ngan-hang-tmcp-hang-hai-viet-nam.htm","Row":1533,"TotalRecord":3172},{"ID":1223,"CatID":5,"Exchange":"UPCoM","IndustryName":"Trung gian tín dụng và các hoạt động liên quan","Code":"KLB","Name":"Ngân hàng TMCP Kiên Long","TotalShares":323695796,"URL":"https://finance.vietstock.vn/KLB-ngan-hang-tmcp-kien-long.htm","Row":1534,"TotalRecord":3172},{"ID":1176,"CatID":1,"Exchange":"HOSE","IndustryName":"Trung gian tín dụng và các hoạt động liên quan","Code":"TCB","Name":"Ngân hàng TMCP Kỹ thương Việt Nam","TotalShares":3504906230,"URL":"https://finance.vietstock.vn/TCB-ngan-hang-tmcp-ky-thuong-viet-nam.htm","Row":1535,"TotalRecord":3172},{"ID":1172,"CatID":5,"Exchange":"UPCoM","IndustryName":"Trung gian tín dụng và các hoạt động liên quan","Code":"NAB","Name":"Ngân hàng TMCP Nam Á","TotalShares":456446843,"URL":"https://finance.vietstock.vn/NAB-ngan-hang-tmcp-nam-a.htm","Row":1536,"TotalRecord":3172},{"ID":1167,"CatID":1,"Exchange":"HOSE","IndustryName":"Trung gian tín dụng và các hoạt động liên quan","Code":"VCB","Name":"Ngân hàng TMCP Ngoại thương Việt Nam","TotalShares":3708877448,"URL":"https://finance.vietstock.vn/VCB-ngan-hang-tmcp-ngoai-thuong-viet-nam.htm","Row":1537,"TotalRecord":3172},{"ID":1195,"CatID":1,"Exchange":"HOSE","IndustryName":"Trung gian tín dụng và các hoạt động liên quan","Code":"HDB","Name":"Ngân hàng TMCP Phát triển TPHCM","TotalShares":1608848818,"URL":"https://finance.vietstock.vn/HDB-ngan-hang-tmcp-phat-trien-tphcm.htm","Row":1538,"TotalRecord":3172},{"ID":1199,"CatID":1,"Exchange":"HOSE","IndustryName":"Trung gian tín dụng và các hoạt động liên quan","Code":"OCB","Name":"Ngân hàng TMCP Phương Đông","TotalShares":1095906343,"URL":"https://finance.vietstock.vn/OCB-ngan-hang-tmcp-phuong-dong.htm","Row":1539,"TotalRecord":3172},{"ID":1190,"CatID":1,"Exchange":"HOSE","IndustryName":"Trung gian tín dụng và các hoạt động liên quan","Code":"MBB","Name":"Ngân hàng TMCP Quân Đội","TotalShares":2798756872,"URL":"https://finance.vietstock.vn/MBB-ngan-hang-tmcp-quan-doi.htm","Row":1540,"TotalRecord":3172},{"ID":1210,"CatID":2,"Exchange":"HNX","IndustryName":"Trung gian tín dụng và các hoạt động liên quan","Code":"NVB","Name":"Ngân hàng TMCP Quốc Dân","TotalShares":410155587,"URL":"https://finance.vietstock.vn/NVB-ngan-hang-tmcp-quoc-dan.htm","Row":1541,"TotalRecord":3172},{"ID":278,"CatID":1,"Exchange":"HOSE","IndustryName":"Trung gian tín dụng và các hoạt động liên quan","Code":"VIB","Name":"Ngân hàng TMCP Quốc tế Việt Nam","TotalShares":1109387852,"URL":"https://finance.vietstock.vn/VIB-ngan-hang-tmcp-quoc-te-viet-nam.htm","Row":1542,"TotalRecord":3172},{"ID":1208,"CatID":2,"Exchange":"HNX","IndustryName":"Trung gian tín dụng và các hoạt động liên quan","Code":"SHB","Name":"Ngân hàng TMCP Sài Gòn - Hà Nội","TotalShares":1926048837,"URL":"https://finance.vietstock.vn/SHB-ngan-hang-tmcp-sai-gon-ha-noi.htm","Row":1543,"TotalRecord":3172},{"ID":1174,"CatID":5,"Exchange":"UPCoM","IndustryName":"Trung gian tín dụng và các hoạt động liên quan","Code":"SGB","Name":"Ngân hàng TMCP Sài Gòn Công Thương","TotalShares":308000000,"URL":"https://finance.vietstock.vn/SGB-ngan-hang-tmcp-sai-gon-cong-thuong.htm","Row":1544,"TotalRecord":3172},{"ID":59,"CatID":1,"Exchange":"HOSE","IndustryName":"Trung gian tín dụng và các hoạt động liên quan","Code":"STB","Name":"Ngân hàng TMCP Sài Gòn Thương Tín","TotalShares":1885215716,"URL":"https://finance.vietstock.vn/STB-ngan-hang-tmcp-sai-gon-thuong-tin.htm","Row":1545,"TotalRecord":3172},{"ID":1987,"CatID":1,"Exchange":"HOSE","IndustryName":"Trung gian tín dụng và các hoạt động liên quan","Code":"TPB","Name":"Ngân hàng TMCP Tiên Phong","TotalShares":1071671722,"URL":"https://finance.vietstock.vn/TPB-ngan-hang-tmcp-tien-phong.htm","Row":1546,"TotalRecord":3172},{"ID":1175,"CatID":1,"Exchange":"HOSE","IndustryName":"Trung gian tín dụng và các hoạt động liên quan","Code":"VPB","Name":"Ngân hàng TMCP Việt Nam Thịnh Vượng","TotalShares":2456748366,"URL":"https://finance.vietstock.vn/VPB-ngan-hang-tmcp-viet-nam-thinh-vuong.htm","Row":1547,"TotalRecord":3172},{"ID":1480,"CatID":5,"Exchange":"UPCoM","IndustryName":"Trung gian tín dụng và các hoạt động liên quan","Code":"VBB","Name":"Ngân hàng TMCP Việt Nam Thương Tín","TotalShares":419019904,"URL":"https://finance.vietstock.vn/VBB-ngan-hang-tmcp-viet-nam-thuong-tin.htm","Row":1548,"TotalRecord":3172},{"ID":1218,"CatID":5,"Exchange":"UPCoM","IndustryName":"Trung gian tín dụng và các hoạt động liên quan","Code":"PGB","Name":"Ngân hàng TMCP Xăng dầu Petrolimex","TotalShares":300000000,"URL":"https://finance.vietstock.vn/PGB-ngan-hang-tmcp-xang-dau-petrolimex.htm","Row":1549,"TotalRecord":3172},{"ID":1171,"CatID":1,"Exchange":"HOSE","IndustryName":"Trung gian tín dụng và các hoạt động liên quan","Code":"EIB","Name":"Ngân hàng TMCP Xuất nhập khẩu Việt Nam","TotalShares":1235522904,"URL":"https://finance.vietstock.vn/EIB-ngan-hang-tmcp-xuat-nhap-khau-viet-nam.htm","Row":1550,"TotalRecord":3172}]